hydrosar/README.md
hydrosar/__init__.py
hydrosar/__main__.py
hydrosar/flood_map.py
hydrosar/threshold.py
hydrosar/water_map.py
hydrosar/data/water_extent.vrt
hydrosar/etc/entrypoint.sh
hydrosar/hand/__init__.py
hydrosar/hand/calculate.py
hydrosar/hand/prepare.py
hydrosar-1.0.0.dist-info/LICENSE
hydrosar-1.0.0.dist-info/METADATA
hydrosar-1.0.0.dist-info/WHEEL
hydrosar-1.0.0.dist-info/entry_points.txt
hydrosar-1.0.0.dist-info/top_level.txt
hydrosar-1.0.0.dist-info/RECORD
