Metadata-Version: 2.1
Name: hydrosar
Version: 1.0.0
Summary: Algorithms for the monitoring of hydrological hazards using data from Synthetic Aperture Radar (SAR) sensors
License: BSD-3-Clause
Project-URL: Homepage, https://github.com/fjmeyer/HydroSAR
Project-URL: Bug Tracker, https://github.com/fjmeyer/HydroSAR/issues
Classifier: Intended Audience :: Science/Research
Classifier: License :: OSI Approved :: BSD License
Classifier: Natural Language :: English
Classifier: Operating System :: OS Independent
Classifier: Programming Language :: Python :: 3
Classifier: Programming Language :: Python :: 3.8
Classifier: Programming Language :: Python :: 3.9
Classifier: Programming Language :: Python :: 3.10
Classifier: Programming Language :: Python :: 3.11
Requires-Python: >=3.8
License-File: LICENSE
Requires-Dist: astropy
Requires-Dist: fiona
Requires-Dist: gdal >=3.3
Requires-Dist: numpy
Requires-Dist: pysheds >=0.3
Requires-Dist: rasterio
Requires-Dist: scikit-fuzzy
Requires-Dist: scikit-image
Requires-Dist: scipy
Requires-Dist: shapely
Requires-Dist: tqdm
Provides-Extra: develop
Requires-Dist: flake8 ; extra == 'develop'
Requires-Dist: flake8-import-order ; extra == 'develop'
Requires-Dist: flake8-blind-except ; extra == 'develop'
Requires-Dist: flake8-builtins ; extra == 'develop'
Requires-Dist: gdal-utils ; extra == 'develop'
Requires-Dist: pytest ; extra == 'develop'
Requires-Dist: pytest-cov ; extra == 'develop'
Requires-Dist: pytest-console-scripts ; extra == 'develop'
